{"web":{"client_id":"401954364511-79pfprpfb3rs39m9hker65ggqihcklbl.apps.googleusercontent.com","project_id":"chrome-reserve-406104","auth_uri":"https://accounts.google.com/o/oauth2/auth","token_uri":"https://oauth2.googleapis.com/token","auth_provider_x509_cert_url":"https://www.googleapis.com/oauth2/v1/certs","client_secret":"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","redirect_uris":["https://wordpressshopcart.com.au/redirect/","http://localhost:3000/redirect/"],"javascript_origins":["http://localhost:3000","https://wordpressshopcart.com.au"]}}